README.md
lungo/__init__.py
lungo/ast.py
lungo/interpreter.py
lungo/lexer.py
lungo/parser.py
lungo/prompt.py
lungo/runtime.py
lungo/sources_cache.py
lungo/token_stream.py
lungo/translator.py
lungo-0.1.2.dist-info/entry_points.txt
lungo-0.1.2.dist-info/WHEEL
lungo-0.1.2.dist-info/METADATA
lungo-0.1.2.dist-info/RECORD
