Metadata-Version: 2.1
Name: lungo
Version: 0.1.2
Summary: 
Home-page: https://github.com/stepan-anokhin/lungo
Author: Stepan Anokhin
Author-email: stepan.anokhin@gmail.com
Requires-Python: >=3.8,<4.0
Classifier: Programming Language :: Python :: 3
Classifier: Programming Language :: Python :: 3.10
Classifier: Programming Language :: Python :: 3.8
Classifier: Programming Language :: Python :: 3.9
Requires-Dist: Pygments (>=2.12.0,<3.0.0)
Requires-Dist: prompt-toolkit (>=3.0.30,<4.0.0)
Project-URL: Repository, https://github.com/stepan-anokhin/lungo
